Axalense/__init__.py
Axalense/axavision.py
Axalense/config.py
Axalense-1.2.87.data/data/LICENSE
Axalense-1.2.87.dist-info/LICENSE
Axalense-1.2.87.dist-info/METADATA
Axalense-1.2.87.dist-info/WHEEL
Axalense-1.2.87.dist-info/top_level.txt
Axalense-1.2.87.dist-info/RECORD
